SheetMachine/Creator.py
SheetMachine/Field.py
SheetMachine/__init__.py
sheetmachine-0.1.0.dist-info/licenses/LICENSE
sheetmachine-0.1.0.dist-info/METADATA
sheetmachine-0.1.0.dist-info/WHEEL
sheetmachine-0.1.0.dist-info/top_level.txt
sheetmachine-0.1.0.dist-info/RECORD
