Metadata-Version: 2.4
Name: SheetMachine
Version: 0.1.0
Summary: Create XLSX files from data
Author: Nicolas Bschor
License:                                  Apache License
Project-URL: Homepage, https://github.com/HackerBschor/SheetMachine
Keywords: excel,data
License-File: LICENSE
Requires-Dist: xlsxwriter>=3.2.9
Dynamic: license-file
